pdf2wordx/__init__.py
pdf2wordx/_pdf2wordx.py
pdf2wordx/favicon.ico
pdf2wordx/ico.ico
pdf2wordx/files/__init__.py
pdf2wordx/files/functions.py
pdf2wordx/files/interfaz.py
pdf2wordx/files/__pycache__/__init__.cpython-312.pyc
pdf2wordx/files/__pycache__/functions.cpython-312.pyc
pdf2wordx/files/__pycache__/interfaz.cpython-312.pyc
pdf2wordx/files/info/NOTICE
pdf2wordx/files/info/help
pdf2wordx_german-1.0.1.dist-info/licenses/LICENSE
pdf2wordx_german-1.0.1.dist-info/METADATA
pdf2wordx_german-1.0.1.dist-info/WHEEL
pdf2wordx_german-1.0.1.dist-info/entry_points.txt
pdf2wordx_german-1.0.1.dist-info/top_level.txt
pdf2wordx_german-1.0.1.dist-info/RECORD
